findtext.py
selenium_findtext-0.1.1.dist-info/COPYING
selenium_findtext-0.1.1.dist-info/METADATA
selenium_findtext-0.1.1.dist-info/WHEEL
selenium_findtext-0.1.1.dist-info/top_level.txt
selenium_findtext-0.1.1.dist-info/zip-safe
selenium_findtext-0.1.1.dist-info/RECORD
