Metadata-Version: 2.1
Name: selenium-findtext
Version: 0.1.1
Summary: Text finding helpers for Selenium tests
Home-page: http://github.com/peaqe/findtext
Author: Calvin Spealman
Author-email: cspealma@redhat.com
License: MIT
Platform: UNKNOWN
